nonebot_plugin_audiocraft/__init__.py
nonebot_plugin_audiocraft-0.0.5.dist-info/WHEEL
nonebot_plugin_audiocraft-0.0.5.dist-info/METADATA
nonebot_plugin_audiocraft-0.0.5.dist-info/RECORD
